Workbook

Sheet Instructions
A1: MS Excel Practical Exam
A2: Total Questions: 30
A3: Difficulty Level: Medium
A4: Syllabus: Formulas, Logical Functions, Lookups, INDEX-MATCH, Pivot Tables & Charts, Data Analysis
A5: Attempt all questions using appropriate Excel tools/functions.

Sheet Pivots
A3: Products | B3: Sum of TotalP_Amount | D3: Regions | E3: Sum of TotalP_Amount
A4: Laptop | B4: 265500 | D4: East | E4: 60480
A5: Mobile | B5: 151200 | D5: North | E5: 173400
A6: Tablet | B6: 60480 | C6: 16 | D6: South | E6: 190200 | F6: 17
A7: Grand Total | B7: 477180 | D7: West | E7: 53100
D8: Grand Total | E8: 477180
A11: Row Labels | B11: Sum of Maths | C11: Sum of Statistics | D11: Sum of Excel
A12: Arjun | B12: 65 | C12: 70 | D12: 72
A13: Pooja | B13: 92 | C13: 89 | D13: 94 | P13: 19
A14: Rahul | B14: 78 | C14: 82 | D14: 85
A15: Sneha | B15: 88 | C15: 91 | D15: 90
A16: Vikas | B16: 55 | C16: 60 | D16: 58 | E16: 18
A17: Grand Total | B17: 378 | C17: 392 | D17: 399

Sheet Sales_Data
A1: Order_ID | B1: Region | C1: Salesperson | D1: Product | E1: Quantity | F1: Unit_Price | G1: Sales_Date | H1: Sales_Amount | I1: GST_Amount | J1: TotalP_Amount | K1: Volume | L1: Month | M1: Category | N1: Left2Letters | O1: RoundUnit
A2: 301 | B2: North | C2: Amit | D2: Laptop | E2: 2 | F2: 45000 | G2: 05-01-2025 | H2: =E2*F2 -> 90000 | I2: =VLOOKUP(D2,Product_Master!$A$2:$C$4,3,0)*H2/100 -> 16200 | J2: =H2+I2 -> 106200 | K2: =IF(E2>3,"High","Low") -> Low | L2: =TEXT(G2,"mmmm") -> January | M2: =INDEX(Product_Master!$A$2:$C$4,MATCH(D2,Product_Master!$A$2:$A$4,0),2) -> Electronics | N2: =LEFT(C2,2) -> Am | O2: =ROUND(F2,1) -> 45000
A3: 306 | B3: South | C3: Riya | D3: Laptop | E3: 2 | F3: 45000 | G3: 18-01-2025 | H3: =E3*F3 -> 90000 | I3: =VLOOKUP(D3,Product_Master!$A$2:$C$4,3,0)*H3/100 -> 16200 | J3: =H3+I3 -> 106200 | K3: =IF(E3>3,"High","Low") -> Low | L3: =TEXT(G3,"mmmm") -> January | M3: =INDEX(Product_Master!$A$2:$C$4,MATCH(D3,Product_Master!$A$2:$A$4,0),2) -> Electronics | N3: =LEFT(C3,2) -> Ri | O3: =ROUND(F3,1) -> 45000 | P3: 1,2,3,7,9,11 23,24,27
A4: 302 | B4: South | C4: Riya | D4: Mobile | E4: 5 | F4: 15000 | G4: 07-01-2025 | H4: =E4*F4 -> 75000 | I4: =VLOOKUP(D4,Product_Master!$A$2:$C$4,3,0)*H4/100 -> 9000 | J4: =H4+I4 -> 84000 | K4: =IF(E4>3,"High","Low") -> High | L4: =TEXT(G4,"mmmm") -> January | M4: =INDEX(Product_Master!$A$2:$C$4,MATCH(D4,Product_Master!$A$2:$A$4,0),2) -> Electronics | N4: =LEFT(C4,2) -> Ri | O4: =ROUND(F4,1) -> 15000
A5: 305 | B5: North | C5: Amit | D5: Mobile | E5: 4 | F5: 15000 | G5: 15-01-2025 | H5: =E5*F5 -> 60000 | I5: =VLOOKUP(D5,Product_Master!$A$2:$C$4,3,0)*H5/100 -> 7200 | J5: =H5+I5 -> 67200 | K5: =IF(E5>3,"High","Low") -> High | L5: =TEXT(G5,"mmmm") -> January | M5: =INDEX(Product_Master!$A$2:$C$4,MATCH(D5,Product_Master!$A$2:$A$4,0),2) -> Electronics | N5: =LEFT(C5,2) -> Am | O5: =ROUND(F5,1) -> 15000
A6: 303 | B6: East | C6: Kunal | D6: Tablet | E6: 3 | F6: 18000 | G6: 10-01-2025 | H6: =E6*F6 -> 54000 | I6: =VLOOKUP(D6,Product_Master!$A$2:$C$4,3,0)*H6/100 -> 6480 | J6: =H6+I6 -> 60480 | K6: =IF(E6>3,"High","Low") -> Low | L6: =TEXT(G6,"mmmm") -> January | M6: =INDEX(Product_Master!$A$2:$C$4,MATCH(D6,Product_Master!$A$2:$A$4,0),2) -> Electronics | N6: =LEFT(C6,2) -> Ku | O6: =ROUND(F6,1) -> 18000
A7: 304 | B7: West | C7: Neha | D7: Laptop | E7: 1 | F7: 45000 | G7: 45669 | H7: =E7*F7 -> 45000 | I7: =VLOOKUP(D7,Product_Master!$A$2:$C$4,3,0)*H7/100 -> 8100 | J7: =H7+I7 -> 53100 | K7: =IF(E7>3,"High","Low") -> Low | L7: =TEXT(G7,"mmmm") -> January | M7: =INDEX(Product_Master!$A$2:$C$4,MATCH(D7,Product_Master!$A$2:$A$4,0),2) -> Electronics | N7: =LEFT(C7,2) -> Ne | O7: =ROUND(F7,1) -> 45000
A8: Grand Total: | H8: =SUM(J2:J7) -> 477180 | Q8: 4,5,8
A9: Max Total Amount: | H9: =MAX(J2:J7) -> 106200
A10: Min Total Amount: | H10: =MIN(J2:J7) -> 53100
A11: Total Orders: | H11: =COUNTA(A2:A7) -> 6
A12: No. of Orders in North | H12: =COUNTIFS(D2:D7,"Laptop",B2:B7,"North") -> 1 | N12: 26
A13: Sort Function | M13: Region-wise Total Sales
A14: {=_xlfn._xlws.SORT(A1:J7,10,-1)} -> Order_ID | B14: Region | C14: Salesperson | D14: Product | E14: Quantity | F14: Unit_Price | G14: Sales_Date | H14: Sales_Amount | I14: GST_Amount | J14: TotalP_Amount | M14: North | N14: =SUMIF(B2:B7,M14,J2:J6) -> 173400
A15: 301 | B15: North | C15: Amit | D15: Laptop | E15: 2 | F15: 45000 | G15: 05-01-2025 | H15: 90000 | I15: 16200 | J15: 106200 | M15: South | N15: =SUMIF(B3:B8,M15,J3:J7) -> 190200 | P15: 6
A16: 306 | B16: South | C16: Riya | D16: Laptop | E16: 2 | F16: 45000 | G16: 18-01-2025 | H16: 90000 | I16: 16200 | J16: 106200 | K16: 10 | M16: East | N16: =SUMIF(B4:B11,M16,J4:J8) -> 60480
A17: 302 | B17: South | C17: Riya | D17: Mobile | E17: 5 | F17: 15000 | G17: 07-01-2025 | H17: 75000 | I17: 9000 | J17: 84000 | M17: West | N17: =SUMIF(B5:B12,M17,J5:J11) -> 53100
A18: 305 | B18: North | C18: Amit | D18: Mobile | E18: 4 | F18: 15000 | G18: 15-01-2025 | H18: 60000 | I18: 7200 | J18: 67200
A19: 303 | B19: East | C19: Kunal | D19: Tablet | E19: 3 | F19: 18000 | G19: 10-01-2025 | H19: 54000 | I19: 6480 | J19: 60480
A20: 304 | B20: West | C20: Neha | D20: Laptop | E20: 1 | F20: 45000 | G20: 45669 | H20: 45000 | I20: 8100 | J20: 53100
J22: Removed Duplicates
J23: {=INDEX(A2:G7,MATCH(_xlfn.UNIQUE(C2:C7),C2:C7,0),{1,2,3,4,5,6,7})} -> 301 | K23: North | L23: Amit | M23: Laptop | N23: 2 | O23: 45000 | P23: 05-01-2025
J24: 306 | K24: South | L24: Riya | M24: Laptop | N24: 2 | O24: 45000 | P24: 18-01-2025 | R24: 28
A25: Filter | J25: 303 | K25: East | L25: Kunal | M25: Tablet | N25: 3 | O25: 18000 | P25: 10-01-2025
A26: {=_xlfn._xlws.FILTER(A2:G7,(E2:E7>1)*(D2:D7="Laptop"),"")} -> 301 | B26: North | C26: Amit | D26: Laptop | E26: 2 | F26: 45000 | G26: 05-01-2025 | H26: 25 | J26: 304 | K26: West | L26: Neha | M26: Laptop | N26: 1 | O26: 45000 | P26: 45669
A27: 306 | B27: South | C27: Riya | D27: Laptop | E27: 2 | F27: 45000 | G27: 18-01-2025

Sheet Product_Master
A1: Product | B1: Category | C1: GST_%
A2: Laptop | B2: Electronics | C2: 18
A3: Mobile | B3: Electronics | C3: 12
A4: Tablet | B4: Electronics | C4: 12

Sheet Student_Marks
A1: Student_ID | B1: Name | C1: Maths | D1: Statistics | E1: Excel | F1: Attendance_% | G1: AverageMarks | H1: Eligibility | I1: Student_code
A2: 1 | B2: Rahul | C2: 78 | D2: 82 | E2: 85 | F2: 92 | G2: =AVERAGE(C2:F2) -> 84.25 | H2: =IF(F2>=85,"Eligible","Not Eligible") -> Eligible | I2: =_xlfn.CONCAT(A2,"_",B2) -> 1_Rahul
A3: 2 | B3: Sneha | C3: 88 | D3: 91 | E3: 90 | F3: 96 | G3: =AVERAGE(C3:F3) -> 91.25 | H3: =IF(F3>=85,"Eligible","Not Eligible") -> Eligible | I3: =_xlfn.CONCAT(A3,"_",B3) -> 2_Sneha | K3: 12,15,22 | N3: 29,30
A4: 3 | B4: Arjun | C4: 65 | D4: 70 | E4: 72 | F4: 85 | G4: =AVERAGE(C4:F4) -> 73 | H4: =IF(F4>=85,"Eligible","Not Eligible") -> Eligible | I4: =_xlfn.CONCAT(A4,"_",B4) -> 3_Arjun
A5: 4 | B5: Pooja | C5: 92 | D5: 89 | E5: 94 | F5: 98 | G5: =AVERAGE(C5:F5) -> 93.25 | H5: =IF(F5>=85,"Eligible","Not Eligible") -> Eligible | I5: =_xlfn.CONCAT(A5,"_",B5) -> 4_Pooja
A6: 5 | B6: Vikas | C6: 55 | D6: 60 | E6: 58 | F6: 80 | G6: =AVERAGE(C6:F6) -> 63.25 | H6: =IF(F6>=85,"Eligible","Not Eligible") -> Not Eligible | I6: =_xlfn.CONCAT(A6,"_",B6) -> 5_Vikas
A9: Topper: | E9: =INDEX(B2:G6,MATCH(MAX(G2:G6),G2:G6,0),1) -> Pooja
A10: Students with >90% attendence | E10: =COUNTIF(F2:F6,">90") -> 3 | I10: 13,14,20,21
A11: Median for Statistics Marks | E11: =MEDIAN(D2:D6) -> 82
A12: Standard Deviation for Excel Marks | E12: =_xlfn.STDEV.S(E2:E6) -> 14.737707

Sheet Questions
A1: 1. Calculate Total Sales for each order (Quantity × Unit_Price). | J1: 2
A2: 2. Calculate GST Amount using VLOOKUP from Product_Master. | J2: 2
A3: 3. Find Final Amount payable (Total Sales + GST). | J3: 2
A4: 4. Find Grand Total of Final Amount. | J4: 2
A5: 5. Count total number of orders using COUNTA. | J5: 2
A6: 6. Find Region-wise total sales using SUMIF. | J6: 2
A7: 7. Use IF to classify Quantity as High (>3) or Low (<=3). | J7: 2
A8: 8. Find the maximum and minimum Final Amount. | J8: 2
A9: 9. Extract month name from Sales_Date. | J9: 2
A10: 10. Sort Sales_Data by Final Amount (Descending). | J10: 2
A11: 11. Use INDEX-MATCH to fetch Product Category. | J11: 2
A12: 12. Calculate average marks of each student. | J12: 2
... A30: 30. Protect the Student_Marks sheet. | J30: 2
J32: =SUM(J1:J30) -> 60

Sheet Answers
A1: Remove Duplicates
A2: Order_ID | B2: Region | C2: Salesperson | D2: Product | E2: Quantity | F2: Unit_Price | G2: Sales_Date | I2: {=_xlfn.UNIQUE(C2:G8,0,1)} -> Salesperson | J2: Product | K2: Quantity | L2: Unit_Price | M2: Sales_Date
A3: 301 | B3: North | C3: Amit | D3: Laptop | E3: 2 | F3: 45000 | G3: 05-01-2025 | I3: Amit | J3: Laptop | K3: 2 | L3: 45000 | M3: 05-01-2025
A4: 306 | B4: South | C4: Riya | D4: Laptop | E4: 2 | F4: 45000 | G4: 18-01-2025 | I4: Riya | J4: Laptop | K4: 2 | L4: 45000 | M4: 18-01-2025
A5: 303 | B5: East | C5: Kunal | D5: Tablet | E5: 3 | F5: 18000 | G5: 10-01-2025 | H5: "=>" | I5: Kunal | J5: Tablet | K5: 3 | L5: 18000 | M5: 10-01-2025
A6: 304 | B6: West | C6: Neha | D6: Laptop | E6: 1 | F6: 45000 | G6: 45669 | I6: Neha | J6: Laptop | K6: 1 | L6: 45000 | M6: 45669
